LICENSE
MANIFEST.in
README.txt
local_install_data.py
setup.cfg
setup.py
doc/happydoc/index.html
doc/happydoc/src/sping/README.html
doc/happydoc/src/sping/__init__.py.html
doc/happydoc/src/sping/colors.py.html
doc/happydoc/src/sping/colors_Color.py.html
doc/happydoc/src/sping/index.html
doc/happydoc/src/sping/pagesizes.py.html
doc/happydoc/src/sping/pid.py.html
doc/happydoc/src/sping/pid_AffineMatrix.py.html
doc/happydoc/src/sping/pid_Canvas.py.html
doc/happydoc/src/sping/pid_Font.py.html
doc/happydoc/src/sping/pid_StateSaver.py.html
doc/happydoc/src/sping/stringformat.py.html
doc/happydoc/src/sping/stringformat_StringFormatter.py.html
doc/happydoc/src/sping/stringformat_StringSegment.py.html
doc/happydoc/src/sping/PDF/__init__.py.html
doc/happydoc/src/sping/PDF/index.html
doc/happydoc/src/sping/PDF/pdfdoc.py.html
doc/happydoc/src/sping/PDF/pdfdoc_OutputGrabber.py.html
doc/happydoc/src/sping/PDF/pdfdoc_PDFCatalog.py.html
doc/happydoc/src/sping/PDF/pdfdoc_PDFDocument.py.html
doc/happydoc/src/sping/PDF/pdfdoc_PDFImage.py.html
doc/happydoc/src/sping/PDF/pdfdoc_PDFInfo.py.html
doc/happydoc/src/sping/PDF/pdfdoc_PDFLiteral.py.html
doc/happydoc/src/sping/PDF/pdfdoc_PDFObject.py.html
doc/happydoc/src/sping/PDF/pdfdoc_PDFOutline.py.html
doc/happydoc/src/sping/PDF/pdfdoc_PDFPage.py.html
doc/happydoc/src/sping/PDF/pdfdoc_PDFPageCollection.py.html
doc/happydoc/src/sping/PDF/pdfdoc_PDFStream.py.html
doc/happydoc/src/sping/PDF/pdfdoc_PDFType1Font.py.html
doc/happydoc/src/sping/PDF/pdfgen.py.html
doc/happydoc/src/sping/PDF/pdfgen_Canvas.py.html
doc/happydoc/src/sping/PDF/pdfgen_PDFPathObject.py.html
doc/happydoc/src/sping/PDF/pdfgen_PDFTextObject.py.html
doc/happydoc/src/sping/PDF/pdfgeom.py.html
doc/happydoc/src/sping/PDF/pdfmetrics.py.html
doc/happydoc/src/sping/PDF/pdfmetrics_FontCache.py.html
doc/happydoc/src/sping/PDF/pdfutils.py.html
doc/happydoc/src/sping/PDF/pidPDF.py.html
doc/happydoc/src/sping/PDF/pidPDF_PDFCanvas.py.html
doc/happydoc/src/sping/PIL/__init__.py.html
src/sping.egg-info/PKG-INFO
src/sping.egg-info/SOURCES.txt
src/sping.egg-info/dependency_links.txt
src/sping.egg-info/top_level.txt
