Metadata-Version: 1.0
Name: sping
Version: 1.1.15
Summary: Sping:Simple Platform INdependent Graphics
Home-page: http://sping.sourceforge.net
Author: UNKNOWN
Author-email: UNKNOWN
License: UNKNOWN
Platform: UNKNOWN
